iirosebot/__init__.py
iirosebot/cli.py
iirosebot/main.py
iirosebot/API/__init__.py
iirosebot/API/api_get_config.py
iirosebot/API/api_iirose.py
iirosebot/API/api_load_config.py
iirosebot/API/api_message.py
iirosebot/API/decorator/__init__.py
iirosebot/API/decorator/command.py
iirosebot/globals/__init__.py
iirosebot/globals/globals.py
iirosebot/init/__init__.py
iirosebot/init/main_init.py
iirosebot/log/__init__.py
iirosebot/log/main.py
iirosebot/plugin_system/__init__.py
iirosebot/plugin_system/plugin_init.py
iirosebot/plugin_system/plugin_manage.py
iirosebot/plugin_system/plugin_transfer.py
iirosebot/plugins/__init__.py
iirosebot/plugins/iirose_example.py
iirosebot/plugins/iirose_flow_master.py
iirosebot/plugins/system_plugin_manage.py
iirosebot/utools/__init__.py
iirosebot/utools/compressed_gzip.py
iirosebot/utools/md5_encrypt.py
iirosebot/ws_iirose/__init__.py
iirosebot/ws_iirose/login_bot.py
iirosebot/ws_iirose/ping.py
iirosebot/ws_iirose/transfer_plugin.py
iirosebot/ws_iirose/ws.py
iirosebot-1.7.0.dist-info/LICENSE
iirosebot-1.7.0.dist-info/METADATA
iirosebot-1.7.0.dist-info/WHEEL
iirosebot-1.7.0.dist-info/entry_points.txt
iirosebot-1.7.0.dist-info/top_level.txt
iirosebot-1.7.0.dist-info/RECORD
