Metadata-Version: 2.1
Name: iirosebot
Version: 1.7.0
Summary: 一个用于蔷薇花园(iirose.com)的python机器人框架
Home-page: https://github.com/XCWQW1/iirosebot
Author: XCWQW1
Author-email: 3539757707@qq.com
Requires-Python: >=3.11.4
License-File: LICENSE
Requires-Dist: loguru >=0.7.2
Requires-Dist: requests >=2.31.0
Requires-Dist: pyyaml >=6.0.1
Requires-Dist: numpy >=1.26.1
Requires-Dist: pillow >=10.3.0
Requires-Dist: configparser >=5.0.2
Requires-Dist: fastapi >=0.109.2
Requires-Dist: openai >=1.10.0
Requires-Dist: art >=6.1
Requires-Dist: langdetect >=1.0.9
